Workbook
Name communication: Overview!$J$4:$J$9
Name not_communicative_at_all: Overview!$J$7:$J$8

Sheet Overview
A1: Candidate name:
A2: Interviewer name:
A3: Date of technical interview
A4: Communication in English: | B4: Please assess English language proficiency... | J4: Please assess English language proficiency...
A5: Coding Task: | B5: Other | J5: Not assessed
A6: Coding Task description: | B6: Describe your coding task if "other" is selected above | J6: Not communicative at all
A7: Overall impression, with assessed seniority and ability to grow: | J7: Poor English / strong accent
A8: Template version | B8: 8.3.1 | J8: Good English / light accent | Q8: familiar | R8: junior
J9: Proficient
A12: Section | F12: Score | G12: Section result | H12: Enable / Disable section | M12: Enabled
A13: =Java!C8 -> 1. Coding task (just discuss possible solutions) | F13: =IF($H$13="Enabled",Java!E13,"-") -> - | G13: =IF($H$13="Enabled",Java!F13,"-") -> not assessed | H13: Enabled | M13: Disabled
A14: =Java!C14 -> 2. CS basics, Algorithms & Data structures | F14: =IF($H$14="Enabled",Java!E34,"-") -> - | G14: =IF($H$14="Enabled",Java!F34,"-") -> not assessed | H14: Enabled
A15: =Java!C35 -> 3. Collections | F15: =IF($H$15="Enabled",Java!E48,"-") -> - | G15: =IF($H$15="Enabled",Java!F48,"-") -> not assessed | H15: Enabled
A16: =Java!C49 -> 4. Java basics | F16: =IF($H$16="Enabled",Java!E64,"-") -> - | G16: =IF($H$16="Enabled",Java!F64,"-") -> not assessed | H16: Enabled
A17: =Java!C65 -> 5. Exceptions | F17: =IF($H$17="Enabled",Java!E78,"-") -> - | G17: =IF($H$17="Enabled",Java!F78,"-") -> not assessed | H17: Enabled
A18: =Java!C79 -> 6. Memory & GC | F18: =IF($H$18="Enabled",Java!E97,"-") -> - | G18: =IF($H$18="Enabled",Java!F97,"-") -> not assessed | H18: Enabled
A19: =Java!C98 -> 7. Modern Java Versions Specifics | F19: =IF($H$19="Enabled",Java!E115,"-") -> - | G19: =IF($H$19="Enabled",Java!F115,"-") -> not assessed | H19: Enabled
A20: =Java!C116 -> 8. Multithreading | F20: =IF($H$20="Enabled",Java!E138,"-") -> - | G20: =IF($H$20="Enabled",Java!F138,"-") -> not assessed | H20: Enabled
A21: =Java!C139 -> 9. OOP | F21: =IF($H$21="Enabled",Java!E145,"-") -> - | G21: =IF($H$21="Enabled",Java!F145,"-") -> not assessed | H21: Enabled
A22: =Java!C146 -> 10. Design patterns | F22: =IF($H$22="Enabled",Java!E158,"-") -> - | G22: =IF($H$22="Enabled",Java!F158,"-") -> not assessed | H22: Enabled
A23: =Java!C159 -> 11. Clean Code | F23: =IF($H$23="Enabled",Java!E165,"-") -> - | G23: =IF($H$23="Enabled",Java!F165,"-") -> not assessed | H23: Enabled
A24: =Java!C166 -> 12. Testing | F24: =IF($H$24="Enabled",Java!E175,"-") -> - | G24: =IF($H$24="Enabled",Java!F175,"-") -> not assessed | H24: Enabled
A25: =Java!C176 -> 13. Spring | F25: =IF($H$25="Enabled",Java!E190,"-") -> - | G25: =IF($H$25="Enabled",Java!F190,"-") -> not assessed | H25: Enabled
A26: =Java!C191 -> 14. Spring Boot | F26: =IF($H$26="Enabled",Java!E199,"-") -> - | G26: =IF($H$25="Enabled",Java!F199,"-") -> not assessed | H26: Enabled
A27: =Java!C200 -> 15. Microservices | F27: =IF($H$27="Enabled",Java!E208,"-") -> - | G27: =IF($H$27="Enabled",Java!F208,"-") -> not assessed | H27: Enabled
A28: =Java!C209 -> 16. Hibernate / JPA | F28: =IF($H$28="Enabled",Java!E235,"-") -> - | G28: =IF($H$28="Enabled",Java!F235,"-") -> not assessed | H28: Enabled
A29: =Java!C236 -> 17. SQL | F29: =IF($H$29="Enabled",Java!E264,"-") -> - | G29: =IF($H$29="Enabled",Java!F264,"-") -> not assessed | H29: Enabled
A30: =Java!C265 -> 18. Unix and networking | F30: =IF($H$30="Enabled",Java!E274,"-") -> - | G30: =IF($H$30="Enabled",Java!F274,"-") -> not assessed | H30: Enabled
A31: =Java!C275 -> 19. JMS / Kafka | F31: =IF($H$31="Enabled",Java!E288,"-") -> - | G31: =IF($H$31="Enabled",Java!F288,"-") -> not assessed | H31: Enabled
A32: =Java!C289 -> 20. Cloud | F32: - | G32: =IF($H$32="Enabled",Java!F290,"-") -> not assessed | H32: Enabled
G33: =IF(_xlfn.IFNA(MATCH("not assessed",G13:G32,0),0)>0,"Assessement incomplete!","") -> Assessement incomplete!

Sheet Java
G1: not assessed
C2: Mandatory sections marked with this colour must be assessed. If a candidate has no experience, select "Insufficient" against any question. All other sections should be assessed if candidate claims he has experience. Feel free to use Custom Question to ask your onw questions - and specify what question was asked. | F2: 1 | G2: insufficient | H2: Candidate is ignorant about the subject, knows little but its name , can't recall any details or has some misbeliefs about it
F3: 2 | G3: junior | H3: Candidate has basic idea about the subject, able to use it in some simple scenario, lacks details about some obvious (regular) scenario
F4: 3 | G4: regular | H4: Candidate has knowledge sufficient to use the subject in most everyday scenario, may lack details about some advanced usage scenario, but no misbeliefs
F5: 4 | G5: senior | H5: Candidate has knowledge sufficient to use the subject in all advanced scenario discussed
F6: 5 | G6: expert | H6: Candidate has comprehensive knowledge on the subject, can teach the subject or act as an expert on it
G7: not assessed
C8: 1. Coding task (just discuss possible solutions) | D8: max | E8: Score | F8: Seniority | G8: Comments (if answered partially)
A9: M | B9: All | C9: Coding task (if over phone, discuss only possible solution) | D9: 5 | E9: =IF(F9=$G$2, 1, IF(F9=$G$3,2, IF(F9=$G$4,3,IF(F9=$G$5,4,IF(F9=$G$6,5,IF(F9=$G$7,0)))))) -> 0 | F9: not assessed
A10: M | C10: Complexity of solved coding task | D10: 5 | E10: =IF(F10=$G$2, 1, IF(F10=$G$3,2, IF(F10=$G$4,3,IF(F10=$G$5,4,IF(F10=$G$6,5,IF(F10=$G$7,0)))))) -> 0 | F10: not assessed
A11: M | C11: Coding task optimization | D11: 5 | E11: =IF(F11=$G$2, 1, IF(F11=$G$3,2, IF(F11=$G$4,3,IF(F11=$G$5,4,IF(F11=$G$6,5,IF(F11=$G$7,0)))))) -> 0 | F11: not assessed
C12: Custom question | D12: 5 | E12: =IF(F12=$G$2, 1, IF(F12=$G$3,2, IF(F12=$G$4,3,IF(F12=$G$5,4,IF(F12=$G$6,5,IF(F12=$G$7,0)))))) -> 0 | F12: not assessed
D13: =IF(B13="", D12, IF(OR(B13="Junior", B13="Regular"), 3, 5)) -> 5 | E13: =IFERROR(AVERAGEIF(E9:E12, "<>0"),"-") -> - | F13: =IFERROR(LOOKUP(E13,Technical!$A$2:$B$8,Technical!$C$2:$C$8),"not assessed") -> not assessed
C14: 2. CS basics, Algorithms & Data structures | D14: =IF(B14="", D13, IF(OR(B14="Junior", B14="Regular"), 3, 5)) -> 5
B15: Junior | C15: Data structures e.g. Stack vs queue | D15: =IF(B15="", D14, IF(OR(B15="Junior", B15="Regular"), 3, 5)) -> 3 | E15: =IF(F15=$G$2, 1, IF(F15=$G$3,2, IF(F15=$G$4,3,IF(F15=$G$5,4,IF(F15=$G$6,5,IF(F15=$G$7,0)))))) -> 0 | F15: not assessed | J15: Stacks A stack is a linear data structure that follows the Last In, First Out (LIFO) principle. This means that the last element added to the stack is the first one to be removed. It can be visualized as a pile of plates where you can only add or remove the top plate. A queue is a linear data structure that follows the First In, First Out (FIFO) principle. This means that the first element added to the queue is the first one to be removed. It can be visualized as a line of people waiting for a service, where the first person in line is the first to be served.
C16: Boolean operations, short circuits in Boolean operations | D16: =IF(B16="", D15, IF(OR(B16="Junior", B16="Regular"), 3, 5)) -> 3 | E16: =IF(F16=$G$2, 1, IF(F16=$G$3,2, IF(F16=$G$4,3,IF(F16=$G$5,4,IF(F16=$G$6,5,IF(F16=$G$7,0)))))) -> 0 | F16: not assessed
A17: M | C17: Complexity of algorithms, big O notation (can be discussed during coding task) | D17: =IF(B17="", D16, IF(OR(B17="Junior", B17="Regular"), 3, 5)) -> 3 | E17: =IF(F17=$G$2, 1, IF(F17=$G$3,2, IF(F17=$G$4,3,IF(F17=$G$5,4,IF(F17=$G$6,5,IF(F17=$G$7,0)))))) -> 0 | F17: not assessed
A18: At least one is mandatory | C18: Trees, graphs and ways to traverse graph | D18: =IF(B18="", D17, IF(OR(B18="Junior", B18="Regular"), 3, 5)) -> 3 | E18: =IF(F18=$G$2, 1, IF(F18=$G$3,2, IF(F18=$G$4,3,IF(F18=$G$5,4,IF(F18=$G$6,5,IF(F18=$G$7,0)))))) -> 0 | F18: not assessed | I18: The tree data structure is a type of graph. A tree has a root node (top node) that will have a relationship with its child nodes. The path that connects the root node to the child nodes is called a branch. The leaf node is the node that doesn’t have any children and is not the root node. In algorithms, you will see a lot of the nomenclature height. Height in trees is the number of nodes from the highest branch to the root node. Another keyword is the depth of a tree which means the count of nodes from a specific node to the root node. A graph is a data structure for storing connected data such as a network of people on a social media platform. There are two possible ways to traverse a graph: depth-first traversal and breadth-first traversal. A depth-first traversal starts at an arbitrary root vertex and explores vertices as deep as possible along each branch before exploring vertices at the same level. breadth-first traversal starts at an arbitrary root vertex and explores all neighboring vertices at the same level before going deeper in the graph.
C19: Sorting algorithms | D19: =IF(B19="", D18, IF(OR(B19="Junior", B19="Regular"), 3, 5)) -> 3 | E19: =IF(F19=$G$2, 1, IF(F19=$G$3,2, IF(F19=$G$4,3,IF(F19=$G$5,4,IF(F19=$G$6,5,IF(F19=$G$7,0)))))) -> 0 | F19: not assessed | I19: Bubble Sort is the simplest sorting algorithm that works by repeatedly swapping the adjacent elements if they are in the wrong order. This algorithm is not suitable for large data sets as its average and worst-case time complexity are quite high. The Merge Sort algorithm is a divide-and-conquer algorithm that sorts an array by first breaking it down into smaller arrays, and then building the array back together the correct way so that it is sorted. QuickSort is a sorting algorithm based on the Divide and Conquer that picks an element as a pivot and partitions the given array around the picked pivot by placing the pivot in its correct position in the sorted array.
B20: Regular | C20: Recursion, tail recursion, mutual recursion | D20: =IF(B20="", D19, IF(OR(B20="Junior", B20="Regular"), 3, 5)) -> 3 | E20: =IF(F20=$G$2, 1, IF(F20=$G$3,2, IF(F20=$G$4,3,IF(F20=$G$5,4,IF(F20=$G$6,5,IF(F20=$G$7,0)))))) -> 0 | F20: not assessed | I20: Recursion is the process where a function self-calls itself to find the result. The base condition acts as the breakpoint to the self-calling process. Tail Recursion A recursive function is a tail recursive when a recursive call is the last thing executed by the function. Mutual Recursion This happens where one method, say method A, calls another method B, which then calls method A. This involves two or more methods that eventually create a circular call sequence. Direct and indirect recursion A function fun is called direct recursive if it calls the same function fun. A function fun is called indirect recursive if it calls another function say fun_new and fun_new calls fun directly or indirectly.
C21: Binary tree / Self balanced trees (Red-black tree, AVL, Splay) | D21: =IF(B21="", D20, IF(OR(B21="Junior", B21="Regular"), 3, 5)) -> 3 | E21: =IF(F21=$G$2, 1, IF(F21=$G$3,2, IF(F21=$G$4,3,IF(F21=$G$5,4,IF(F21=$G$6,5,IF(F21=$G$7,0)))))) -> 0 | F21: not assessed | I21: Binary Tree A tree in which each node (parent) has at most two-child nodes (left and right) is called binary tree. The top most node is called the root node. In a binary tree a node contains the data and the pointer (address) of the left and right child node. mainly used for sorting and searching because they store data in hierarchical form. A red-black tree is a self-balancing binary search tree, that is, a binary search tree that automatically maintains some balance. Each node is assigned a color (red or black). A set of rules specifies how these colors must be arranged (e.g., a red node may not have red children) AVL tree is another self-balancing BST(Binary Search Tree) in Java. In the AVL tree, the difference between heights of the right and left subtree doesn't exceed one for all nodes. It takes O(h) time to perform the search, max, min, insert, and delete BST operations. A splay tree is a self-balancing tree, but AVL and Red-Black trees are also self-balancing trees then. What makes the splay tree unique two trees. It has one extra property that makes it unique is splaying. A splay tree contains the same operations as a Binary search tree, i.e., Insertion, deletion and searching, but it also contains one more operation, i.e., splaying. So. all the operations in the splay tree are followed by splaying.All normal operations on a binary search tree are combined with one basic operation, called splaying. Splaying the tree for a certain element rearranges the tree so that the element is placed at the root of the tree.
C22: Search in binary tree | D22: =IF(B22="", D21, IF(OR(B22="Junior", B22="Regular"), 3, 5)) -> 3 | E22: =IF(F22=$G$2, 1, IF(F22=$G$3,2, IF(F22=$G$4,3,IF(F22=$G$5,4,IF(F22=$G$6,5,IF(F22=$G$7,0)))))) -> 0 | F22: not assessed | I22: Depth-first search is a type of traversal that goes deep as much as possible in every child before exploring the next sibling. There are several ways to perform a depth-first search: in-order, pre-order and post-order. The in-order traversal consists of first visiting the left sub-tree, then the root node, and finally the right sub-tree. Pre-order traversal visits first the root node, then the left sub-tree, and finally the right sub-tree. Post-order traversal visits the left sub-tree, the right subt-ree, and the root node at the end Breadth-First Search This kind of traversal is also called level-order, and visits all the levels of the tree starting from the root, and from left to right.
C23: Linear-time sorting. (count sort) | D23: =IF(B23="", D22, IF(OR(B23="Junior", B23="Regular"), 3, 5)) -> 3 | E23: =IF(F23=$G$2, 1, IF(F23=$G$3,2, IF(F23=$G$4,3,IF(F23=$G$5,4,IF(F23=$G$6,5,IF(F23=$G$7,0)))))) -> 0 | F23: not assessed | I23: Linear time sorting is a subset of sorting algorithms with a significant advantage: they can sort a given set of elements in linear time, the runtime increases linearly with the input size. The best-known linear time sorting algorithm is descending sort. Computational sorting is particularly efficient when the range of input elements is known and relatively small. This eliminates the need to compare elements, the main time-consuming operation in many other sorting algorithms. | Q23: 1 find max num 2 create array with max size 3 fill occurrences of each num in origina array 4 sum occurrences: index 0 equal 1 then 1. index 1 equal 3 plus index 0 equal 1 sum is equal 4, index 2 equal 0 plus index 1 sum equal 4, index 3 equal 2 plus index2 sum equal 6 5 for each element in the original array look in count array for its next position: 1 starts in position 1, then it is added in the output array in index 1, count array index 1 plus1 so it is now 2 0, starts in index 0 according with count array, so added in index 0 of output array, count array index 0 value is now 1. 3 starts in index4 according to count array, add 3 at index 4 in output array, index 3of count array is now equal 5 1 starts now in index 2, so a 1 is added at index 2 in output array, index 1 is now equal to 3 in count array 3 starts now at index 5, in output array index 5 we add a 3, index 3 is now equal to 6 in count array 1 is now equal to 3 in count array, we go to index 3 in output array and add a 1, 1 is now equal to 4 in count array
C24: Sorting of linked list. | D24: =IF(B24="", D23, IF(OR(B24="Junior", B24="Regular"), 3, 5)) -> 3 | E24: =IF(F24=$G$2, 1, IF(F24=$G$3,2, IF(F24=$G$4,3,IF(F24=$G$5,4,IF(F24=$G$6,5,IF(F24=$G$7,0)))))) -> 0 | F24: not assessed | J24: For linked lists, Merge Sort is often the best choice because: Merge Sort guarantees a time complexity of O(nlogn) in the average, best, and worst cases. Merge Sort is Stable Merge Sort naturally fits well with Linked List because it traverses items in sequential manner (no random access) When we compare linked list implementation with the array implementation we can notice that the linked list implementation does not require extra space to merge because linked list allows insertion and deletion in the middle in O(1) time.
B25: Senior | C25: Prefix and suffix trees | D25: 5 | E25: =IF(F25=$G$2, 1, IF(F25=$G$3,2, IF(F25=$G$4,3,IF(F25=$G$5,4,IF(F25=$G$6,5,IF(F25=$G$7,0)))))) -> 0 | F25: not assessed | J25: prefix tree or trie. is an ordered tree structure, which takes advantage of the keys that it stores – usually strings. In a trie, every node (except the root node) stores one character or a digit. By traversing the trie down from the root node to a particular node n, a common prefix of characters or digits can be formed which is shared by other branches of the trie as well. | V25: A suffix tree is simply a compressed suffix trie. What this means is that, by joining the edges, we can store a group of characters and thereby reduce the storage space significantly. A suffix tree also stores the position of the suffix in the leaf node. For example, BANANA$ is a suffix starting from the seventh position. Hence, its value will be six using zero-based numbering. Likewise, A->BANANA$ is another suffix starting at position five,
C26: Describe heap | D26: =IF(B25="", D25, IF(OR(B25="Junior", B25="Regular"), 3, 5)) -> 5 | E26: =IF(F26=$G$2, 1, IF(F26=$G$3,2, IF(F26=$G$4,3,IF(F26=$G$5,4,IF(F26=$G$6,5,IF(F26=$G$7,0)))))) -> 0 | F26: not assessed | I26: Heap space is used for the dynamic memory allocation of Java objects and JRE classes at runtime. New objects are always created in heap space, and the references to these objects are stored in stack memory. These objects have global access and we can access them from anywhere in the application. Unlike stack, a heap isn’t threadsafe and needs to be guarded by properly synchronizing the code. If heap space is full, Java throws java.lang.OutOfMemoryError. Heap memory is used by all the parts of the application whereas stack memory is used only by one thread of execution. Whenever an object is created, it’s always stored in the Heap space and stack memory contains the reference to it. Stack memory only contains local primitive variables and reference variables to objects in heap space. Stack memory is short-lived whereas heap memory lives from the start till the end of application execution. When stack memory is full, Java runtime throws java.lang.StackOverFlowError whereas if heap memory is full, it throws java.lang.OutOfMemoryError: Java Heap Space error.
C27: Greedy Algorithm | D27: =IF(B27="", D26, IF(OR(B27="Junior", B27="Regular"), 3, 5)) -> 5 | E27: =IF(F27=$G$2, 1, IF(F27=$G$3,2, IF(F27=$G$4,3,IF(F27=$G$5,4,IF(F27=$G$6,5,IF(F27=$G$7,0)))))) -> 0 | F27: not assessed | J27: Greedy algorithms are a class of algorithms that make locally optimal choices at each step with the hope of finding a global optimum solution. In these algorithms, decisions are made based on the information available at the current moment without considering the consequences of these decisions in the future. The key idea is to select the best possible choice at each step, leading to a solution that may not always be the most optimal but is often good enough for many problems.It operates on the principle of “taking the best option now” without considering the long-term consequences.
C28: NP-complete algorithms | D28: =IF(B28="", D27, IF(OR(B28="Junior", B28="Regular"), 3, 5)) -> 5 | E28: =IF(F28=$G$2, 1, IF(F28=$G$3,2, IF(F28=$G$4,3,IF(F28=$G$5,4,IF(F28=$G$6,5,IF(F28=$G$7,0)))))) -> 0 | F28: not assessed | J28: NP stands for Non-deterministic Polynomial time. This means that the problem can be solved in Polynomial time using a Non-deterministic Turing machine (like a regular Turing machine but also including a non-deterministic "choice" function). Basically, a solution has to be testable in poly time. If that's the case, and a known NP problem can be solved using the given problem with modified input (an NP problem can be reduced to the given problem) then the problem is NP complete.
C29: Map/reduce and divide and conquer approach in solving tasks | D29: =IF(B29="", D28, IF(OR(B29="Junior", B29="Regular"), 3, 5)) -> 5 | E29: =IF(F29=$G$2, 1, IF(F29=$G$3,2, IF(F29=$G$4,3,IF(F29=$G$5,4,IF(F29=$G$6,5,IF(F29=$G$7,0)))))) -> 0 | F29: not assessed | J29: MapReduce is a programming model used for efficient processing in parallel over large data-sets in a distributed manner. The data is first split and then combined to produce the final result. | N29: A divide-and-conquer algorithm recursively breaks down a problem into two or more sub-problems of the same or related type, until these become simple enough to be solved directly. The solutions to the sub-problems are then combined to give a solution to the original problem.
C30: Dynamic programming | D30: =IF(B30="", D29, IF(OR(B30="Junior", B30="Regular"), 3, 5)) -> 5 | E30: =IF(F30=$G$2, 1, IF(F30=$G$3,2, IF(F30=$G$4,3,IF(F30=$G$5,4,IF(F30=$G$6,5,IF(F30=$G$7,0)))))) -> 0 | F30: not assessed | J30: Dynamic Programming is a method used in mathematics and computer science to solve complex problems by breaking them down into simpler subproblems. By solving each subproblem only once and storing the results, it avoids redundant computations, leading to more efficient solutions for a wide range of problems. How Does Dynamic Programming (DP) Work? Identify Subproblems: Divide the main problem into smaller, independent subproblems. Store Solutions: Solve each subproblem and store the solution in a table or array. Build Up Solutions: Use the stored solutions to build up the solution to the main problem. Avoid Redundancy: By storing solutions, DP ensures that each subproblem is solved only once, reducing computation time. ivide and conquer is a strategy for separating a problem into smaller sections and addressing each one separately. In contrast, dynamic programming is a strategy for solving larger issues by breaking them down into smaller pieces.
C31: How would you fix a cyclic dependency | D31: =IF(B31="", D30, IF(OR(B31="Junior", B31="Regular"), 3, 5)) -> 5 | E31: =IF(F31=$G$2, 1, IF(F31=$G$3,2, IF(F31=$G$4,3,IF(F31=$G$5,4,IF(F31=$G$6,5,IF(F31=$G$7,0)))))) -> 0 | F31: not assessed | J31: Cyclic dependencies occur when two or more components depend on each other directly or indirectly. Cyclic dependencies introduce several main drawbacks: Tight Coupling: Components become tightly coupled, making it difficult to change or reuse them independently. Unintended Side Effects: Changes in one component can have unexpected and difficult-to-debug side effects on other components within the cycle. By applying the Dependency Inversion Principle (DIP), you can break circular dependencies. For example, we can fix the circular dependency in our example above by introducing a new module that serves as a stable interface both the app module and module2 can depend on.
C32: What is the difference between static and dynamic typing? Duck typing? | D32: 5 | E32: =IF(F32=$G$2, 1, IF(F32=$G$3,2, IF(F32=$G$4,3,IF(F32=$G$5,4,IF(F32=$G$6,5,IF(F32=$G$7,0)))))) -> 0 | F32: not assessed | J32: Static Typing Static typing is a typing system where variables are bound to a data type during compilation. Once a variable is assigned a data type it remains unchanged throughout the programs execution. This binding promotes type safety and detects errors at an early stage. One of the advantages of typing is ensuring type safety which reduces the chances of runtime errors caused by mismatches in data types. ex, java, c++ Dynamic Typing In contrast, dynamic typing allows variables to be bound to data types at runtime instead of during compilation. This flexibility enables concise code and ease of use. It compromises on type safety as a trade-off. ex: js Duck typing In computer programming, duck typing is an application of the duck test—"If it walks like a duck and it quacks like a duck, then it must be a duck"—to determine whether an object can be used for a particular purpose. With duck typing, an object is of a given type if it has all methods and properties required by that type
B33: All | C33: Custom question | D33: =IF(B33="", D31, IF(OR(B33="Junior", B33="Regular"), 3, 5)) -> 5 | E33: =IF(F33=$G$2, 1, IF(F33=$G$3,2, IF(F33=$G$4,3,IF(F33=$G$5,4,IF(F33=$G$6,5,IF(F33=$G$7,0)))))) -> 0 | F33: not assessed
D34: =IF(B34="", D33, IF(OR(B34="Junior", B34="Regular"), 3, 5)) -> 5 | E34: =IFERROR(AVERAGEIF(E15:E33, "<>0"),"-") -> - | F34: =IFERROR(LOOKUP(E34,Technical!$A$2:$B$8,Technical!$C$2:$C$8),"not assessed") -> not assessed
C35: 3. Collections | D35: =IF(B35="", D34, IF(OR(B35="Junior", B35="Regular"), 3, 5)) -> 5
A36: At least one is mandatory | B36: Regular | C36: General collection interfaces (Collection, Set, Map, List, Queue, SortedSet, SortedMap) | D36: =IF(B36="", D35, IF(OR(B36="Junior", B36="Regular"), 3, 5)) -> 3 | E36: =IF(F36=$G$2, 1, IF(F36=$G$3,2, IF(F36=$G$4,3,IF(F36=$G$5,4,IF(F36=$G$6,5,IF(F36=$G$7,0)))))) -> 0 | F36: not assessed | I36: Queue: The queue is an abstract data type or linear data structure from which elements can be inserted at the rear(back) of the queue and elements can be deleted from the front(head) of the queue. Deque: The double-ended queue is an abstract data type that generalizes a queue from which elements can be inserted or deleted either from both front(head) or rear(tail) ends. SortedSet: A Set that further provides a total ordering on its elements. The elements are ordered using their natural ordering, or by a Comparator typically provided at sorted set creation time. The set's iterator will traverse the set in ascending element order. Several additional operations are provided to take advantage of the ordering. This means that when you iterate the elements of a SortedSet the elements are iterated in the sorted order. SortedMap: The Java SortedMap interface, java.util.SortedMap, is a subtype of the java.util.Map interface, with the addition that the elements stored in a Java SortedMap map are sorted internally. This means you can iterate the elements stored in a SortedMap in the sort order. SortedMap sortedMap = new TreeMap(); Comparator comparator = new MyComparatorImpl(); SortedMap sortedMap = new TreeMap(comparator); the keys of a SortedMap are sorted iterate the keys in descending order rather than ascending order, use the sortedMap.descendingKeySet().iterator()
C37: Interfaces extending Collection. Is Map part of Collection interface | D37: =IF(B37="", D36, IF(OR(B37="Junior", B37="Regular"), 3, 5)) -> 3 | E37: =IF(F37=$G$2, 1, IF(F37=$G$3,2, IF(F37=$G$4,3,IF(F37=$G$5,4,IF(F37=$G$6,5,IF(F37=$G$7,0)))))) -> 0 | F37: not assessed
C38: Difference between ArrayList and LinkedList | D38: =IF(B38="", D37, IF(OR(B38="Junior", B38="Regular"), 3, 5)) -> 3 | E38: =IF(F38=$G$2, 1, IF(F38=$G$3,2, IF(F38=$G$4,3,IF(F38=$G$5,4,IF(F38=$G$6,5,IF(F38=$G$7,0)))))) -> 0 | F38: not assessed | J38: ArrayList nternally, ArrayList is using an array to implement the List interface. As arrays are fixed size in Java, ArrayList creates an array with some initial capacity. Along the way, if we need to store more items than that default capacity, it will replace that array with a new and more spacious one. Accessing items by their indices is where the ArrayList really shines. To retrieve an item at index i, we just have to return the item residing at the ith index from the backing array. Consequently, the time complexity for access by index operation is always O(1). , it’s actually a sensible choice when the number of reads is far more than the number of writes. LinkedList uses a collection of linked nodes to store and retrieve elements. the time complexity for the add operation is always O(1). LinkedList, as opposed to ArrayList, does not support fast random access. So, in order to find an element by index, we should traverse some portion of the list manually. LinkedLists are more suitable when the addition rate is much higher than the read rate. Also, it can be used in read-heavy scenarios when most of the time we want the first or last element. It’s worth mentioning that LinkedList also implements the Deque interface – supporting efficient access to both ends of the collection.
C39: Difference between Stack and Queue | D39: =IF(B39="", D38, IF(OR(B39="Junior", B39="Regular"), 3, 5)) -> 3 | E39: =IF(F39=$G$2, 1, IF(F39=$G$3,2, IF(F39=$G$4,3,IF(F39=$G$5,4,IF(F39=$G$6,5,IF(F39=$G$7,0)))))) -> 0 | F39: not assessed | J39: Stacks A stack is a linear data structure that follows the Last In, First Out (LIFO) principle. This means that the last element added to the stack is the first one to be removed. It can be visualized as a pile of plates where you can only add or remove the top plate. A queue is a linear data structure that follows the First In, First Out (FIFO) principle. This means that the first element added to the queue is the first one to be removed. It can be visualized as a line of people waiting for a service, where the first person in line is the first to be served.
C40: TreeSet vs TreeMap | D40: =IF(B40="", D39, IF(OR(B40="Junior", B40="Regular"), 3, 5)) -> 3 | E40: =IF(F40=$G$2, 1, IF(F40=$G$3,2, IF(F40=$G$4,3,IF(F40=$G$5,4,IF(F40=$G$6,5,IF(F40=$G$7,0)))))) -> 0 | F40: not assessed
B41: Senior | C41: Internal structure of HashMap/Hashtable | D41: =IF(B41="", D40, IF(OR(B41="Junior", B41="Regular"), 3, 5)) -> 5 | E41: =IF(F41=$G$2, 1, IF(F41=$G$3,2, IF(F41=$G$4,3,IF(F41=$G$5,4,IF(F41=$G$6,5,IF(F41=$G$7,0)))))) -> 0 | F41: not assessed | I41: A hash table uses a hash function to compute an index, also called a hash code, into an array of buckets or slots, from which the desired value can be found. During lookup, the supplied key is hashed, and the resulting hash indicates where the corresponding value is stored in the Hash table hashCode() method is used to get the hash code of an object. hashCode() method of the object class returns the memory reference of an object in integer form. HashMap uses equals() to compare the key to whether they are equal or not. If the equals() method return true, they are equal otherwise not equal. Buckets: A bucket is an element of the HashMap array. It is used to store nodes. Hash Collision This is the case when the calculated index value is the same for two or more Keys. The better the hashing algorithm that we use to compute hash codes, the better the performance of hash tables.
C42: Requirements for implementation of hashCode to achieve best performance | D42: =IF(B42="", D41, IF(OR(B42="Junior", B42="Regular"), 3, 5)) -> 5 | E42: =IF(F42=$G$2, 1, IF(F42=$G$3,2, IF(F42=$G$4,3,IF(F42=$G$5,4,IF(F42=$G$6,5,IF(F42=$G$7,0)))))) -> 0 | F42: not assessed | I42: Equal objects should have the same hash code. Whenever it is invoked on the same object more than once during an execution of a Java application, the hashCode method must consistently return the same integer It is not required that if two objects are unequal according to the equals(Object) method, then calling the hashCode method on each of the two objects must produce distinct integer results. However, the programmer should be aware that producing distinct integer results for unequal objects may improve the performance of hash tables.
C43: Definition and ways of resolving collisions in hash tables | D43: =IF(B43="", D42, IF(OR(B43="Junior", B43="Regular"), 3, 5)) -> 5 | E43: =IF(F43=$G$2, 1, IF(F43=$G$3,2, IF(F43=$G$4,3,IF(F43=$G$5,4,IF(F43=$G$6,5,IF(F43=$G$7,0)))))) -> 0 | F43: not assessed | I43: a hash code collision in a HashMap, is a situation where two or more key objects produce the same final hash value and hence point to the same bucket location. This scenario can occur because according to the equals and hashCode contract, two unequal objects in Java can have the same hash code. It can also happen because of the finite size of the underlying array, that is, before resizing. The smaller this array, the higher the chances of collision. Keep in mind that it’s the hash value of the key that determines the bucket the object will be stored in. And so, if the hash codes of any two keys collide, their entries will still be stored in the same bucket. And by default, the implementation uses a linked list as the bucket implementation. resolution techniques: 1) Separate Chaining Separate chaining is a technique that uses linked lists to store elements with the same hash value. In case of a collision, the new element is simply added to the end of the linked list at the corresponding index. 2) Open Addressing Open addressing is another collision resolution technique where all elements are stored in the same table. In case of a collision, a new index is calculated using a probing sequence until an empty slot is found. Some common techniques for open addressing include linear probing, quadratic probing, and double hashing. Linear Probing: In linear probing, after a collision, search adjacent buckets until an empty spot or the desired element is found. If the next bucket is occupied, move to the next one and repeat. Linear probing can lead to clustering. Quadratic Probing: Quadratic Probing is similar to linear probing but uses quadratic increments (1, 3, 6, 10, 15, …) away from the collision point. Quadratic probing helps reduce clustering. Double Hashing: In double hashing, we use a second hash function to determine the step size for probing. Calculate the next bucket as hash(key) + i * hash2(key). Double hashing provides better distribution than linear or quadratic probing.
C44: Differences between Hashtable and ConcurrentHashMap | D44: =IF(B44="", D43, IF(OR(B44="Junior", B44="Regular"), 3, 5)) -> 5 | E44: =IF(F44=$G$2, 1, IF(F44=$G$3,2, IF(F44=$G$4,3,IF(F44=$G$5,4,IF(F44=$G$6,5,IF(F44=$G$7,0)))))) -> 0 | F44: not assessed | J44: ConcurrentHashMap uses multiple buckets to store data. This avoids read locks and greatly improves performance over a HashTable. Both are thread safe, but there are obvious performance wins with ConcurrentHashMap. When you read from a ConcurrentHashMap using get(), there are no locks, contrary to the HashTable for which all operations are simply synchronized. HashTable was released in old versions of Java whereas ConcurrentHashMap is a java 5+ thing. While both Hashtable and ConcurrentHashMap guarantee thread safety, they differ in performance due to their underlying synchronization mechanisms. Hashtable locks the entire table during a write operation, thereby preventing other reads or writes. This could be a bottleneck in a high-concurrency environment. ConcurrentHashMap, however, allows concurrent reads and limited concurrent writes, making it more scalable and often faster in practice.
C45: Special versions of collections. EnumSet, EnumMap, WeakHaskMap, IdentityHashMap. | D45: =IF(B45="", D44, IF(OR(B45="Junior", B45="Regular"), 3, 5)) -> 5 | E45: =IF(F45=$G$2, 1, IF(F45=$G$3,2, IF(F45=$G$4,3,IF(F45=$G$5,4,IF(F45=$G$6,5,IF(F45=$G$7,0)))))) -> 0 | F45: not assessed | I45: The EnumSet is one of the specialized implementations of the Set interface for use with the enumeration type. EnumSet is faster than HashSet because we no need to compute any hashCode to find the right bucket. EnumMap is a specialized implementation of the Map interface for enumeration types. EnumMap is an ordered collection and they are maintained in the natural order of their keys(the natural order of keys means the order on which enum constants are declared inside enum type ). It’s a high-performance map implementation, much faster than HashMap. WeakHashMap. It’s a high-performance map implementation, much faster than HashMap. WeakHashMap is a hashtable-based implementation of the Map interface, with keys that are of a WeakReference type. An entry in a WeakHashMap will automatically be removed when its key is no longer in ordinary use, meaning that there is no single Reference that point to that key. When the garbage collection (GC) process discards a key, its entry is effectively removed from the map, so this class behaves somewhat differently from other Map implementations. The IdentityHashMap implements Map interface using Hashtable, using reference-equality in place of object-equality when comparing keys (and values). This class is not a general-purpose Map implementation. While this class implements the Map interface, it intentionally violates Map’s general contract, which mandates the use of the equals() method when comparing objects. This class is used when the user requires the objects to be compared via reference.
C46: Iterator and modification of a List. ConcurentModificationException. Collections with safe iterators (CopyOnWriteArrayList/CopyOnWriteArraySet) | D46: =IF(B46="", D44, IF(OR(B46="Junior", B46="Regular"), 3, 5)) -> 5 | E46: =IF(F46=$G$2, 1, IF(F46=$G$3,2, IF(F46=$G$4,3,IF(F46=$G$5,4,IF(F46=$G$6,5,IF(F46=$G$7,0)))))) -> 0 | F46: not assessed | I46: A ConcurrentModificationException is a RuntimeException that is thrown when a collection is modified while it is being iterated over. This often happens when you try to add or remove elements from a collection, like a list, during iteration Luckily, we can use several methods to safely make changes to our collection while iterating over it, which won’t throw an exception. 1. Use the Iterator’s add() and/or remove() methods One method is to make use of Java’s Iterator interface and its add() and remove() methods to safely modify a collection during iteration. Use a Concurrent Collection If you need to handle collections in a multi-threaded environment, consider using a concurrent collection, such as ConcurrentHashMap, CopyOnWriteArrayList, or CopyOnWriteArraySet. These collections are designed to be safely modified by multiple threads without causing a ConcurrentModificationException. Keep in mind that concurrent collections may have slightly lower performance compared to their non-concurrent counterparts due to the overhead of synchronisation.
B47: All | C47: Custom question | D47: =IF(B47="", D45, IF(OR(B47="Junior", B47="Regular"), 3, 5)) -> 5 | E47: =IF(F47=$G$2, 1, IF(F47=$G$3,2, IF(F47=$G$4,3,IF(F47=$G$5,4,IF(F47=$G$6,5,IF(F47=$G$7,0)))))) -> 0 | F47: not assessed
D48: =IF(B48="", D47, IF(OR(B48="Junior", B48="Regular"), 3, 5)) -> 5 | E48: =IFERROR(AVERAGEIF(E36:E47, "<>0"),"-") -> - | F48: =IFERROR(LOOKUP(E48,Technical!$A$2:$B$8,Technical!$C$2:$C$8),"not assessed") -> not assessed
C49: 4. Java basics | D49: =IF(B49="", D48, IF(OR(B49="Junior", B49="Regular"), 3, 5)) -> 5
A50: At least one is mandatory | B50: Junior | C50: Length in bytes/max value for primitive types | D50: =IF(B50="", D49, IF(OR(B50="Junior", B50="Regular"), 3, 5)) -> 3 | E50: =IF(F50=$G$2, 1, IF(F50=$G$3,2, IF(F50=$G$4,3,IF(F50=$G$5,4,IF(F50=$G$6,5,IF(F50=$G$7,0)))))) -> 0 | F50: not assessed
C51: this' and 'super' keywords | D51: =IF(B51="", D50, IF(OR(B51="Junior", B51="Regular"), 3, 5)) -> 3 | E51: =IF(F51=$G$2, 1, IF(F51=$G$3,2, IF(F51=$G$4,3,IF(F51=$G$5,4,IF(F51=$G$6,5,IF(F51=$G$7,0)))))) -> 0 | F51: not assessed
C52: Contract between equals() and hashCode() | D52: =IF(B52="", D51, IF(OR(B52="Junior", B52="Regular"), 3, 5)) -> 3 | E52: =IF(F52=$G$2, 1, IF(F52=$G$3,2, IF(F52=$G$4,3,IF(F52=$G$5,4,IF(F52=$G$6,5,IF(F52=$G$7,0)))))) -> 0 | F52: not assessed | I52: If two objects are equal, they must have the same hash code. If two objects have the same hash code, it does not necessarily mean they are equal. Overriding the equals() method alone would fail with hashing data structures like Map, Set, etc. Overriding the hashCode() method alone would not help in comparing objects.
C53: Access modifiers in Java | D53: =IF(B53="", D52, IF(OR(B53="Junior", B53="Regular"), 3, 5)) -> 3 | E53: =IF(F53=$G$2, 1, IF(F53=$G$3,2, IF(F53=$G$4,3,IF(F53=$G$5,4,IF(F53=$G$6,5,IF(F53=$G$7,0)))))) -> 0 | F53: not assessed
C54: What different between StringBuffer and StringBuilder | D54: =IF(B54="", D53, IF(OR(B54="Junior", B54="Regular"), 3, 5)) -> 3 | E54: =IF(F54=$G$2, 1, IF(F54=$G$3,2, IF(F54=$G$4,3,IF(F54=$G$5,4,IF(F54=$G$6,5,IF(F54=$G$7,0)))))) -> 0 | F54: not assessed
B55: Regular | C55: What does it mean that an object or a class is mutable or immutable | D55: =IF(B55="", D54, IF(OR(B55="Junior", B55="Regular"), 3, 5)) -> 3 | E55: =IF(F55=$G$2, 1, IF(F55=$G$3,2, IF(F55=$G$4,3,IF(F55=$G$5,4,IF(F55=$G$6,5,IF(F55=$G$7,0)))))) -> 0 | F55: not assessed
C56: How to make class immutable | D56: =IF(B56="", D55, IF(OR(B56="Junior", B56="Regular"), 3, 5)) -> 3 | E56: =IF(F56=$G$2, 1, IF(F56=$G$3,2, IF(F56=$G$4,3,IF(F56=$G$5,4,IF(F56=$G$6,5,IF(F56=$G$7,0)))))) -> 0 | F56: not assessed | I56: The class must be declared as final so that child classes can’t be created. Data members in the class must be declared private so that direct access is not allowed. Data members in the class must be declared as final so that we can’t change the value of it after object creation. A parameterized constructor should initialize all the fields performing a deep copy so that data members can’t be modified with an object reference. Deep Copy of objects should be performed in the getter methods to return a copy rather than returning the actual object reference)
C57: Besides “string” do you know any other immutable classes | D57: =IF(B57="", D56, IF(OR(B57="Junior", B57="Regular"), 3, 5)) -> 3 | E57: =IF(F57=$G$2, 1, IF(F57=$G$3,2, IF(F57=$G$4,3,IF(F57=$G$5,4,IF(F57=$G$6,5,IF(F57=$G$7,0)))))) -> 0 | F57: not assessed | I57: Immutable class in java means that once an object is created, we cannot change its content. In Java, all the wrapper classes (like Integer, Boolean, Byte, Short) and String class is immutable.
C58: Rules to create equals method | D58: =IF(B58="", D57, IF(OR(B58="Junior", B58="Regular"), 3, 5)) -> 3 | E58: =IF(F58=$G$2, 1, IF(F58=$G$3,2, IF(F58=$G$4,3,IF(F58=$G$5,4,IF(F58=$G$6,5,IF(F58=$G$7,0)))))) -> 0 | F58: not assessed | I58: Since every Java class inherits from the Object class, and Object implements the equals() method – every Java class by default implements equals(). The implicit implementation compares objects by their reference, and this is often not the right solution. It has to be reflexive, so for any non-null value, x.equals(x) should return true. It has to be symmetric, so for any non-null value when x.equals(y) returns true, then y.equals(x) has to return true as well. It has to be transitive, so for any non-null value if x.equals(y) returns true and y.equals(z) returns true, then x.equals(z) has to return true. It has to be consistent, so multiple invocations of x.equals(y) have to return the same value for each call. It has to return false for any non-null value calling x.equals(null).
C59: Difference between overriding and overloading | D59: =IF(B59="", D58, IF(OR(B59="Junior", B59="Regular"), 3, 5)) -> 3 | E59: =IF(F59=$G$2, 1, IF(F59=$G$3,2, IF(F59=$G$4,3,IF(F59=$G$5,4,IF(F59=$G$6,5,IF(F59=$G$7,0)))))) -> 0 | F59: not assessed
C60: How can we replace multi-inheritance pattern in Java | D60: =IF(B60="", D59, IF(OR(B60="Junior", B60="Regular"), 3, 5)) -> 3 | E60: =IF(F60=$G$2, 1, IF(F60=$G$3,2, IF(F60=$G$4,3,IF(F60=$G$5,4,IF(F60=$G$6,5,IF(F60=$G$7,0)))))) -> 0 | F60: not assessed | J60: by using interfaces
C61: Can interface inherit from different interface | D61: =IF(B61="", D60, IF(OR(B61="Junior", B61="Regular"), 3, 5)) -> 3 | E61: =IF(F61=$G$2, 1, IF(F61=$G$3,2, IF(F61=$G$4,3,IF(F61=$G$5,4,IF(F61=$G$6,5,IF(F61=$G$7,0)))))) -> 0 | F61: not assessed | J61: yes using the extends keyword
C62: Regular vs. static initialization blocks | D62: =IF(B62="", D61, IF(OR(B62="Junior", B62="Regular"), 3, 5)) -> 3 | E62: =IF(F62=$G$2, 1, IF(F62=$G$3,2, IF(F62=$G$4,3,IF(F62=$G$5,4,IF(F62=$G$6,5,IF(F62=$G$7,0)))))) -> 0 | F62: not assessed | J62: a static block executes code before the object initialization. | Q62: the purpose of the instance initializer block is to initialize the instance data members. Static initializer blocks always execute before the instance initialization blocks because static blocks run at the time of class loading. However, the instance block runs at the time of instance creation. The Java compiler copies initializer blocks into every constructor.
B63: All | C63: Custom question | D63: 5 | E63: =IF(F63=$G$2, 1, IF(F63=$G$3,2, IF(F63=$G$4,3,IF(F63=$G$5,4,IF(F63=$G$6,5,IF(F63=$G$7,0)))))) -> 0 | F63: not assessed
D64: =IF(B64="", D63, IF(OR(B64="Junior", B64="Regular"), 3, 5)) -> 5 | E64: =IFERROR(AVERAGEIF(E50:E63, "<>0"),"-") -> - | F64: =IFERROR(LOOKUP(E64,Technical!$A$2:$B$8,Technical!$C$2:$C$8),"not assessed") -> not assessed
C65: 5. Exceptions | D65: =IF(B65="", D64, IF(OR(B65="Junior", B65="Regular"), 3, 5)) -> 5
A66: At least one is mandatory | B66: Regular | C66: Checked vs. unchecked exceptions. Why would one use former or later? | D66: =IF(B66="", D65, IF(OR(B66="Junior", B66="Regular"), 3, 5)) -> 3 | E66: =IF(F66=$G$2, 1, IF(F66=$G$3,2, IF(F66=$G$4,3,IF(F66=$G$5,4,IF(F66=$G$6,5,IF(F66=$G$7,0)))))) -> 0 | F66: not assessed | I66: Checked Exceptions in Java These are the exceptions that are checked at compile time. If some code within a method throws a checked exception, then the method must either handle the exception or it must specify the exception using the throws keyword. Checked exceptions can be fully checked or partially checked. Fully Checked Exception: A checked exception where all its child classes are also checked (e.g., IOException, InterruptedException). Partially Checked Exception: A checked exception where some of its child classes are unchecked (e.g., Exception). Unchecked Exceptions in Java These are the exceptions that are not checked at compile time. In Java, exceptions under Error and RuntimeException classes are unchecked exceptions, everything else under throwable is checked. In short unchecked exceptions are runtime exceptions that are not required to be caught or declared in a throws clause. These exceptions are usually caused by programming errors, such as attempting to access an index out of bounds in an array or attempting to divide by zero.
C67: Difference in Error and UncheckedException | D67: =IF(B67="", D66, IF(OR(B67="Junior", B67="Regular"), 3, 5)) -> 3 | E67: =IF(F67=$G$2, 1, IF(F67=$G$3,2, IF(F67=$G$4,3,IF(F67=$G$5,4,IF(F67=$G$6,5,IF(F67=$G$7,0)))))) -> 0 | F67: not assessed | I67: An Error is a subclass of Throwable that indicates serious problems that a reasonable application should not try to catch. Most such errors are abnormal conditions. even though an unchecked exception is not required to be caught, you may want to. An error, you don't want to catch.
C68: Could we have only try and finally without catch | D68: =IF(B68="", D67, IF(OR(B68="Junior", B68="Regular"), 3, 5)) -> 3 | E68: =IF(F68=$G$2, 1, IF(F68=$G$3,2, IF(F68=$G$4,3,IF(F68=$G$5,4,IF(F68=$G$6,5,IF(F68=$G$7,0)))))) -> 0 | F68: not assessed | I68: yes
C69: Cases when the finally block isn't executed | D69: =IF(B69="", D68, IF(OR(B69="Junior", B69="Regular"), 3, 5)) -> 3 | E69: =IF(F69=$G$2, 1, IF(F69=$G$3,2, IF(F69=$G$4,3,IF(F69=$G$5,4,IF(F69=$G$6,5,IF(F69=$G$7,0)))))) -> 0 | F69: not assessed | I69: If you call System.exit(0) in the try. Or make something that makes the JVM quit or hang (like a deadlock). Otherwise
B70: Senior | C70: What is exception handling mechanism | D70: =IF(B70="", D69, IF(OR(B70="Junior", B70="Regular"), 3, 5)) -> 5 | E70: =IF(F70=$G$2, 1, IF(F70=$G$3,2, IF(F70=$G$4,3,IF(F70=$G$5,4,IF(F70=$G$6,5,IF(F70=$G$7,0)))))) -> 0 | F70: not assessed | I70: Exception Handling is a mechanism to handle runtime errors such as ClassNotFoundException, IOException, SQLException, RemoteException, etc. The core advantage of exception handling is to maintain the normal flow of the application. An exception normally disrupts the normal flow of the application; that is why we need to handle exceptions.
C71: Java Exceptions API | D71: =IF(B71="", D70, IF(OR(B71="Junior", B71="Regular"), 3, 5)) -> 5 | E71: =IF(F71=$G$2, 1, IF(F71=$G$3,2, IF(F71=$G$4,3,IF(F71=$G$5,4,IF(F71=$G$6,5,IF(F71=$G$7,0)))))) -> 0 | F71: not assessed
C72: How to avoid catch block | D72: =IF(B72="", D71, IF(OR(B72="Junior", B72="Regular"), 3, 5)) -> 5 | E72: =IF(F72=$G$2, 1, IF(F72=$G$3,2, IF(F72=$G$4,3,IF(F72=$G$5,4,IF(F72=$G$6,5,IF(F72=$G$7,0)))))) -> 0 | F72: not assessed | K72: return statement | M72: dont declare it just add the finally block
C73: What is Multi-Catch catch (ClassCastException | IOException e) | D73: =IF(B73="", D72, IF(OR(B73="Junior", B73="Regular"), 3, 5)) -> 5 | E73: =IF(F73=$G$2, 1, IF(F73=$G$3,2, IF(F73=$G$4,3,IF(F73=$G$5,4,IF(F73=$G$6,5,IF(F73=$G$7,0)))))) -> 0 | F73: not assessed
C74: What is try-with-resources | D74: =IF(B74="", D73, IF(OR(B74="Junior", B74="Regular"), 3, 5)) -> 5 | E74: =IF(F74=$G$2, 1, IF(F74=$G$3,2, IF(F74=$G$4,3,IF(F74=$G$5,4,IF(F74=$G$6,5,IF(F74=$G$7,0)))))) -> 0 | F74: not assessed | J74: java 7 introduced | L74: allows us to declare resources to be used in a try block with the assurance that the resources will be closed after the execution of that block. The resources declared need to implement the AutoCloseable interface.
B75: Expert | C75: What are Suppressed exceptions | D75: =IF(B75="", D74, IF(OR(B75="Junior", B75="Regular"), 3, 5)) -> 5 | E75: =IF(F75=$G$2, 1, IF(F75=$G$3,2, IF(F75=$G$4,3,IF(F75=$G$5,4,IF(F75=$G$6,5,IF(F75=$G$7,0)))))) -> 0 | F75: not assessed | J75: a suppressed exception is an exception that is thrown but somehow ignored. A common scenario for this in Java is when the finally block throws an exception. Any exception originally thrown in the try block is then suppressed. Starting with Java 7, we can now use two methods on the Throwable class to handle our suppressed exceptions: addSuppressed and getSuppressed. ex: file not found exception thrown then in the finally we are closing the file, the first file not found is suppressed and only the null pointer is received we can take advantage of the Throwable.addSuppressed method to provide the original exception: assertThat(e.getSuppressed()[0], instanceOf(FileNotFoundException.class));
C76: NoClassDefFoundError vs ClassNotFoundException | D76: =IF(B76="", D74, IF(OR(B76="Junior", B76="Regular"), 3, 5)) -> 5 | E76: =IF(F76=$G$2, 1, IF(F76=$G$3,2, IF(F76=$G$4,3,IF(F76=$G$5,4,IF(F76=$G$6,5,IF(F76=$G$7,0)))))) -> 0 | F76: not assessed | J76: ClassNotFoundException is a checked exception which occurs when an application tries to load a class through its fully-qualified name and can not find its definition on the classpath. This occurs mainly when trying to load classes using Class.forName(), ClassLoader.loadClass() or ClassLoader.findSystemClass(). Therefore, we need to be extra careful of java.lang.ClassNotFoundException while working with reflection. NoClassDefFoundError is a fatal error. It occurs when JVM can not find the definition of the class while trying to: Instantiate a class by using the new keyword Load a class with a method call The error occurs when a compiler could successfully compile the class, but Java runtime could not locate the class file. It usually happens when there is an exception while executing a static block or initializing static fields of the class, so class initialization fails.
B77: All | C77: Custom question | D77: =IF(B77="", D75, IF(OR(B77="Junior", B77="Regular"), 3, 5)) -> 5 | E77: =IF(F77=$G$2, 1, IF(F77=$G$3,2, IF(F77=$G$4,3,IF(F77=$G$5,4,IF(F77=$G$6,5,IF(F77=$G$7,0)))))) -> 0 | F77: not assessed
D78: =IF(B78="", D77, IF(OR(B78="Junior", B78="Regular"), 3, 5)) -> 5 | E78: =IFERROR(AVERAGEIF(E66:E77, "<>0"),"-") -> - | F78: =IFERROR(LOOKUP(E78,Technical!$A$2:$B$8,Technical!$C$2:$C$8),"not assessed") -> not assessed
C79: 6. Memory & GC | D79: =IF(B79="", D78, IF(OR(B79="Junior", B79="Regular"), 3, 5)) -> 5
A80: At least one is mandatory | B80: Regular | C80: How is virtual heap space divided in Java? (The answer may be version specific) | D80: =IF(B80="", D79, IF(OR(B80="Junior", B80="Regular"), 3, 5)) -> 3 | E80: =IF(F80=$G$2, 1, IF(F80=$G$3,2, IF(F80=$G$4,3,IF(F80=$G$5,4,IF(F80=$G$6,5,IF(F80=$G$7,0)))))) -> 0 | F80: not assessed | I80: Stack in java is a section of memory which contains methods, local variables, and reference variables. Stack memory is always referenced in Last-In-First-Out order. The Stack Memory allocation in java is used for static memory and thread execution. Heap is a section of memory which contains Objects and may also contain reference variables. Instance variables are created in the heap. Mainly used by java runtime, Java Heap Space comes into play every time an object is created and allocated in it. An object created in the Heap Space can have free access across the application.
C81: What difference between float and BigDecimal? How they store the data? | D81: =IF(B81="", D80, IF(OR(B81="Junior", B81="Regular"), 3, 5)) -> 3 | E81: =IF(F81=$G$2, 1, IF(F81=$G$3,2, IF(F81=$G$4,3,IF(F81=$G$5,4,IF(F81=$G$6,5,IF(F81=$G$7,0)))))) -> 0 | F81: not assessed | J81: BigDecimal class represents an immutable, arbitrary-precision, signed decimal number. It can handle numbers of any size without loss of precision. The BigDecimal class offers better precision than Double, as it can perform calculations with arbitrary-precision decimals, avoiding the rounding errors arising from Double’s binary representation. That’s because BigDecimal uses integer arithmetic internally, which is more accurate than floating-point arithmetic. In terms of speed and range, the utilization of hardware-level floating-point arithmetic in Java’s Double makes it faster than BigDecimal. The Double class covers a broad spectrum, accommodating both large and small numbers. However, its confinement within a 64-bit structure introduces precision limitations, especially for extremely large or small numbers. In contrast, BigDecimal presents a more extensive range of values and better precision across a wide array of values. There are also differences in memory usage. Java’s Double is more compact, which results in more efficient memory usage. On the other hand, BigDecimal’s strength in arbitrary-precision arithmetic entails higher memory consumption.
C82: Java object references | D82: =IF(B82="", D81, IF(OR(B82="Junior", B82="Regular"), 3, 5)) -> 3 | E82: =IF(F82=$G$2, 1, IF(F82=$G$3,2, IF(F82=$G$4,3,IF(F82=$G$5,4,IF(F82=$G$6,5,IF(F82=$G$7,0)))))) -> 0 | F82: not assessed | J82: A Reference consists of an ordered list of addresses and class information about the object being referenced.
C83: What is deep copy of a Java object | D83: =IF(B83="", D82, IF(OR(B83="Junior", B83="Regular"), 3, 5)) -> 3 | E83: =IF(F83=$G$2, 1, IF(F83=$G$3,2, IF(F83=$G$4,3,IF(F83=$G$5,4,IF(F83=$G$6,5,IF(F83=$G$7,0)))))) -> 0 | F83: not assessed | J83: Shallow Copy A shallow copy of an object copies all the member fields, but it does not copy objects that the fields refer to. Instead, the references to these objects are copied, meaning both the original and the copied object refer to the same objects. In Java, the clone() method creates a shallow copy by default. Deep Copy A deep copy, on the other hand, duplicates everything directly or indirectly referenced by the fields in the original object. This means the cloned object does not share references with the original object; it creates a completely independent copy.
C84: Disadvantages of setting heap size too high | D84: =IF(B84="", D83, IF(OR(B84="Junior", B84="Regular"), 3, 5)) -> 3 | E84: =IF(F84=$G$2, 1, IF(F84=$G$3,2, IF(F84=$G$4,3,IF(F84=$G$5,4,IF(F84=$G$6,5,IF(F84=$G$7,0)))))) -> 0 | F84: not assessed | I84: Slower Startup: A larger heap size requires more memory allocation during startup, leading to slightly longer startup times for the Java application. the maximum heap size should always be smaller than the amount of memory installed on the machine to avoid excessive page faults and thrashing.
C85: What are utilities for JVM monitoring? | D85: =IF(B85="", D84, IF(OR(B85="Junior", B85="Regular"), 3, 5)) -> 3 | E85: =IF(F85=$G$2, 1, IF(F85=$G$3,2, IF(F85=$G$4,3,IF(F85=$G$5,4,IF(F85=$G$6,5,IF(F85=$G$7,0)))))) -> 0 | F85: not assessed
C86: How to force GC be executed | D86: =IF(B86="", D85, IF(OR(B86="Junior", B86="Regular"), 3, 5)) -> 3 | E86: =IF(F86=$G$2, 1, IF(F86=$G$3,2, IF(F86=$G$4,3,IF(F86=$G$5,4,IF(F86=$G$6,5,IF(F86=$G$7,0)))))) -> 0 | F86: not assessed | J86: Using System.gc() method: System class contain static method gc() for requesting JVM to run Garbage Collector. Using Runtime.getRuntime().gc() method: Runtime class allows the application to interface with the JVM in which the application is running. Hence by using its gc() method, we can request JVM to run Garbage Collector. There is no guarantee that any of the above two methods will run Garbage Collector. The call System.gc() is effectively equivalent to the call : Runtime.getRuntime().gc()
B87: Senior | C87: Garbage collection principles | D87: =IF(B87="", D86, IF(OR(B87="Junior", B87="Regular"), 3, 5)) -> 5 | E87: =IF(F87=$G$2, 1, IF(F87=$G$3,2, IF(F87=$G$4,3,IF(F87=$G$5,4,IF(F87=$G$6,5,IF(F87=$G$7,0)))))) -> 0 | F87: not assessed | J87: Automatic garbage collection is the process of looking at heap memory, identifying which objects are in use and which are not, and deleting the unused objects. An in use object, or a referenced object, means that some part of your program still maintains a pointer to that object. An unused object, or unreferenced object, is no longer referenced by any part of your program. So the memory used by an unreferenced object can be reclaimed. Step 1 Marking. This is where the garbage collector identifies which pieces of memory are in use and which are not. Step 2 Normal Deletion Normal deletion removes unreferenced objects leaving referenced objects and pointers to free space. Step 2a Deletion with Compacting To further improve performance, in addition to deleting unreferenced objects, you can also compact the remaining referenced objects. By moving referenced object together, this makes new memory allocation much easier and faster. Why Generational Garbage Collection? As stated earlier, having to mark and compact all the objects in a JVM is inefficient. As more and more objects are allocated, the list of objects grows and grows leading to longer and longer garbage collection time. However, empirical analysis of applications has shown that most objects are short lived. Moved to Young and Old Generation
C88: What are memory leaks | D88: =IF(B88="", D87, IF(OR(B88="Junior", B88="Regular"), 3, 5)) -> 5 | E88: =IF(F88=$G$2, 1, IF(F88=$G$3,2, IF(F88=$G$4,3,IF(F88=$G$5,4,IF(F88=$G$6,5,IF(F88=$G$7,0)))))) -> 0 | F88: not assessed | J88: A Memory Leak is a situation where there are objects present in the heap that are no longer used, but the garbage collector is unable to remove them from memory, and therefore, they’re unnecessarily maintained. A memory leak is bad because it blocks memory resources and degrades system performance over time. If not dealt with, the application will eventually exhaust its resources, finally terminating with a fatal java.lang.OutOfMemoryError. There are two different types of objects that reside in Heap memory, referenced and unreferenced. Referenced objects are those that still have active references within the application, whereas unreferenced objects don’t have any active references. The garbage collector removes unreferenced objects periodically, but it never collects the objects that are still being referenced. The first scenario that can cause a potential memory leak is heavy use of static variables. In Java, static fields have a life that usually matches the entire lifetime of the running application (unless ClassLoader becomes eligible for garbage collection). Through Unclosed Resources Whenever we make a new connection or open a stream, the JVM allocates memory for these resources. A few examples of this include database connections, input streams, and session objects. Forgetting to close these resources can block the memory, thus keeping them out of the reach of the GC Improper equals() and hashCode() Implementations
C89: What is variable shadowing | D89: =IF(B89="",#REF!, IF(OR( B89="Junior", B89="Regular"), 3, 5)) -> #REF! | E89: =IF(F89=$G$2, 1, IF(F89=$G$3,2, IF(F89=$G$4,3,IF(F89=$G$5,4,IF(F89=$G$6,5,IF(F89=$G$7,0)))))) -> 0 | F89: not assessed | J89: Shadowing in Java is the practice of using variables in overlapping scopes with the same name where the variable in low-level scope overrides the variable of high-level scope. Here the variable at high-level scope is shadowed by the low-level scope variable.
C90: How would you monitor JVM | D90: =IF(B90="", D89, IF(OR(B90="Junior", B90="Regular"), 3, 5)) -> #REF! | E90: =IF(F90=$G$2, 1, IF(F90=$G$3,2, IF(F90=$G$4,3,IF(F90=$G$5,4,IF(F90=$G$6,5,IF(F90=$G$7,0)))))) -> 0 | F90: not assessed
C91: How would you monitor how GC behaves during program execution | D91: =IF(B91="", D90, IF(OR(B91="Junior", B91="Regular"), 3, 5)) -> #REF! | E91: =IF(F91=$G$2, 1, IF(F91=$G$3,2, IF(F91=$G$4,3,IF(F91=$G$5,4,IF(F91=$G$6,5,IF(F91=$G$7,0)))))) -> 0 | F91: not assessed | J91: There are different ways to monitor GC, but the only difference is how the GC operation information is shown. GC is done by JVM, and since the GC monitoring tools disclose the GC information provided by JVM, you will get the same results no matter how you monitor GC. jstat is a monitoring tool in HotSpot JVM. Other monitoring tools for HotSpot JVM are jps and jstatd. Sometimes, you need all three tools to monitor a Java application. jstat does not provide only the GC operation information display. It also provides class loader operation information or Just-in-Time compiler operation information. Among all the information jstat can provide, in this article we will only cover its functionality to monitor GC operating information. jstat is located in $JDK_HOME/bin, so if java or javac can run without setting a separate directory from the command line, so can jstat.
C92: Name few GC implementations (Serial, Parallel, ParallelOld, ConcarentMarkAndSweep) describe major differences | D92: =IF(B92="", D91, IF(OR(B92="Junior", B92="Regular"), 3, 5)) -> #REF! | E92: =IF(F92=$G$2, 1, IF(F92=$G$3,2, IF(F92=$G$4,3,IF(F92=$G$5,4,IF(F92=$G$6,5,IF(F92=$G$7,0)))))) -> 0 | F92: not assessed | J92: Serial Collector The serial collector uses a single thread to perform all garbage collection work, which makes it relatively efficient because there is no communication overhead between threads. It's best-suited to single processor machines because it can't take advantage of multiprocessor hardware, although it can be useful on multiprocessors for applications with small data sets (up to approximately 100 MB). | L92: Parallel Collector The parallel collector is also known as throughput collector, it's a generational collector similar to the serial collector. The primary difference between the serial and parallel collectors is that the parallel collector has multiple threads that are used to speed up garbage collection. The parallel collector is intended for applications with medium-sized to large-sized data sets that are run on multiprocessor or multithreaded hardware. | N92: The Concurrent Mark Sweep (CMS) collector is designed for applications that prefer shorter garbage collection pauses and that can afford to share processor resources with the garbage collector while the application is running. Typically applications that have a relatively large set of long-lived data (a large tenured generation) and run on machines with two or more processors tend to benefit from the use of this collector. However, this collector should be considered for any application with a low pause time requirement.
B93: Expert | C93: Memory model in JVM (happens before, atomicity of memory reads and writes) | D93: =IF(B93="", D92, IF(OR(B93="Junior", B93="Regular"), 3, 5)) -> 5 | E93: =IF(F93=$G$2, 1, IF(F93=$G$3,2, IF(F93=$G$4,3,IF(F93=$G$5,4,IF(F93=$G$6,5,IF(F93=$G$7,0)))))) -> 0 | F93: not assessed
C94: Perm Space vs Metadata space in Java 8 | D94: =IF(B94="", D93, IF(OR(B94="Junior", B94="Regular"), 3, 5)) -> 5 | E94: =IF(F94=$G$2, 1, IF(F94=$G$3,2, IF(F94=$G$4,3,IF(F94=$G$5,4,IF(F94=$G$6,5,IF(F94=$G$7,0)))))) -> 0 | F94: not assessed | I94: PermGen (Permanent Generation) is a special heap space separated from the main memory heap. The JVM keeps track of loaded class metadata in the PermGen. Additionally, the JVM stores all the static content in this memory section. This includes all the static methods, primitive variables, and references to the static objects. Metaspace is a new memory space – starting from the Java 8 version; it has replaced the older PermGen memory space. The most significant difference is how it handles memory allocation. Specifically, this native memory region grows automatically by default. The main difference from a user perspective - which I think the previous answer does not stress enough - is that Metaspace by default auto increases its size (up to what the underlying OS provides), while PermGen always has a fixed maximum size. You can set a fixed maximum for Metaspace with JVM parameters, but you cannot make PermGen auto-increase.
C95: What are G1 of C4 garbage collectors | D95: =IF(B95="", D93, IF(OR(B95="Junior", B95="Regular"), 3, 5)) -> 5 | E95: =IF(F95=$G$2, 1, IF(F95=$G$3,2, IF(F95=$G$4,3,IF(F95=$G$5,4,IF(F95=$G$6,5,IF(F95=$G$7,0)))))) -> 0 | F95: not assessed | I95: Garbage-first (G1) collector is a server-style garbage collector, targeted for multiprocessors with large memories, that meets a soft real-time goal with high probability, while achieving high-throughput.[2] G1 preferentially collects regions with the least amount of live data, or "garbage first"
B96: All | C96: Custom question | D96: =IF(B96="", D94, IF(OR(B96="Junior", B96="Regular"), 3, 5)) -> 5 | E96: =IF(F96=$G$2, 1, IF(F96=$G$3,2, IF(F96=$G$4,3,IF(F96=$G$5,4,IF(F96=$G$6,5,IF(F96=$G$7,0)))))) -> 0 | F96: not assessed
D97: =IF(B97="", D96, IF(OR(B97="Junior", B97="Regular"), 3, 5)) -> 5 | E97: =IFERROR(AVERAGEIF(E80:E96, "<>0"),"-") -> - | F97: =IFERROR(LOOKUP(E97,Technical!$A$2:$B$8,Technical!$C$2:$C$8),"not assessed") -> not assessed
C98: 7. Modern Java Versions Specifics | D98: =IF(B98="", D97, IF(OR(B98="Junior", B98="Regular"), 3, 5)) -> 5
A99: At least one is mandatory | B99: Regular | C99: What is a parameterized or generic type | D99: =IF(B99="", D98, IF(OR(B99="Junior", B99="Regular"), 3, 5)) -> 3 | E99: =IF(F99=$G$2, 1, IF(F99=$G$3,2, IF(F99=$G$4,3,IF(F99=$G$5,4,IF(F99=$G$6,5,IF(F99=$G$7,0)))))) -> 0 | F99: not assessed | I99: jDK 5.0 introduced Java Generics with the aim of reducing bugs and adding an extra layer of abstraction over types List<Integer> list = new LinkedList<>(); Copy By adding the diamond operator <> containing the type, we narrow the specialization of this list to only Integer type. In other words, we specify the type held inside the list. The compiler can enforce the type at compile time. As mentioned, the method can deal with more than one generic type. Where this is the case, we must add all generic types to the method signature. Here is how we would modify the above method to deal with type T and type G: public static <T, G> List<G> fromArrayToList(T[] a, Function<T, G> mapperFunction) { return Arrays.stream(a) .map(mapperFunction) .collect(Collectors.toList()); } @Test public void givenArrayOfIntegers_thanListOfStringReturnedOK() { Integer[] intArray = {1, 2, 3, 4, 5}; List<String> stringList = Generics.fromArrayToList(intArray, Object::toString); assertThat(stringList, hasItems("1", "2", "3", "4", "5")); } Multiple Bounds A type can also have multiple upper bounds: <T extends Number & Comparable> One restriction of generics in Java is that the type parameter cannot be a primitive type. type parameters must be convertible to Object. Since primitive types don’t extend Object, we can’t use them as type parameters. | R99: Using Wildcards With Generics Wildcards are represented by the question mark ? in Java, and we use them to refer to an unknown type. Wildcards are particularly useful with generics and can be used as a parameter type. We know that Object is the supertype of all Java classes. However, a collection of Object is not the supertype of any collection. For example, a List<Object> is not the supertype of List<String>, and assigning a variable of type List<Object> to a variable of type List<String> will cause a compiler error. public static void paintAllBuildings(List<Building> buildings) { buildings.forEach(Building::paint); } Copy If we imagine a subtype of Building, such as a House, we can’t use this method with a list of House, even though House is a subtype of Building. If we need to use this method with type Building and all its subtypes, the bounded wildcard can do the magic: public static void paintAllBuildings(List<? extends Building> buildings) { ... } Now this method will work with type Building and all its subtypes. We can also specify wildcards with a lower bound, where the unknown type has to be a supertype of the specified type. Lower bounds can be specified using the super keyword followed by the specific type. For example, <? super T> means unknown type that is a superclass of T (= T and all its parents). Type Erasure Generics were added to Java to ensure type safety. And to ensure that generics won’t cause overhead at runtime, the compiler applies a process called type erasure on generics at compile time. Type erasure removes all type parameters and replaces them with their bounds or with Object if the type parameter is unbounded. This way, the bytecode after compilation contains only normal classes, interfaces and methods, ensuring that no new types are produced. Proper casting is applied as well to the Object type at compile time.
C100: What is Autoboxing and what are its advantages/pitfalls | D100: =IF(B100="", D99, IF(OR(B100="Junior", B100="Regular"), 3, 5)) -> 3 | E100: =IF(F100=$G$2, 1, IF(F100=$G$3,2, IF(F100=$G$4,3,IF(F100=$G$5,4,IF(F100=$G$6,5,IF(F100=$G$7,0)))))) -> 0 | F100: not assessed | I100: Collections can only hold object references, so you have to box primitive values into the appropriate wrapper class (which is Integer in the case of int). When you take the object out of the collection, you get the Integer that you put in; if you need an int, you must unbox the Integer using the intValue method. All of this boxing and unboxing is a pain, and clutters up your code. The autoboxing and unboxing feature automates the process, eliminating the pain and the clutter. The following example illustrates autoboxing and unboxing, along with generics and the for-each loop. In a mere ten lines of code, it computes and prints an alphabetized frequency table of the words appearing on the command line. import java.util.*; // Prints a frequency table of the words on the command line public class Frequency { public static void main(String[] args) { Map<String, Integer> m = new TreeMap<String, Integer>(); for (String word : args) { Integer freq = m.get(word); m.put(word, (freq == null ? 1 : freq + 1)); } System.out.println(m); } } The program first declares a map from String to Integer, associating the number of times a word occurs on the command line with the word. Then it iterates over each word on the command line. For each word, it looks up the word in the map. Then it puts a revised entry for the word into the map. The line that does this (highlighted in green) contains both autoboxing and unboxing. To compute the new value to associate with the word, first it looks at the current value (freq). If it is null, this is the first occurrence of the word, so it puts 1 into the map. Otherwise, it adds 1 to the number of prior occurrences and puts that value into the map. But of course you cannot put an int into a map, nor can you add one to an Integer. What is really happening is this: In order to add 1 to freq, it is automatically unboxed, resulting in an expression of type int. Since both of the alternative expressions in the conditional expression are of type int, so too is the conditional expression itself. In order to put this int value into the map, it is automatically boxed into an Integer. Advantages eliminating the pain and the clutter of boxing and unboxing, more readable and concise code Pitfalls An Integer expression can have a null value. If your program tries to autounbox null, it will throw a NullPointerException. The == operator performs reference identity comparisons on Integer expressions and value equality comparisons on int expressions. Finally, there are performance costs associated with boxing and unboxing, even if it is done automatically.
...

Sheet Example Coding tasks
A1: Please select one of…
A2: Number of pairs in Array | B2: Write java function which calculates number of pairs in array. Pair is when two numbers added together, result is zero.
A3: Traverse tree | B3: Write java function to find some element in binary search tree
A4: Reverse List | B4: Write java function to reverse elements in one directional linked list
A5: Merge sorted arrays | B5: Having two separate sorted arrays, write java function merging these arrays in single sorted array without sorting it
A6: Find duplicate number in array | B6: An array contains numbers. Exactly one number is duplicated in the array. Write java function to find this duplicate | E6: We have an array {8,7,5,1,5,3,4}. As you can see there is exactly one number duplicated in the array (number 5). Write a java function to return this duplicate number (method is expected to return 5 as a result)
A7: Find number in matrix | B7: In a 2D matrix, every row ins increasingly sorted from left to right. Last number in each row is not greater then first number in next row. Write java function to check if there is a number in the matrix
A8: Find number of occurrences in array | B8: Write java function to find number of occurrences of some number in given array of numbers
A9: Other | B9: We have the following map of contacts, we want to take this map and return a list of all phones which exist in the map. (in this case we would expect to return a list with 6 phone numbers). Using java 8 stream operations. | E9: We have the following map: Map<String, List<String>> people = new HashMap<>(); people.put("John", Arrays.asList("555-1123", "555-3389")); people.put("Mary", Arrays.asList("555-2243", "555-5264")); people.put("Steve", Arrays.asList("555-6654", "555-3242")); using java 8 get a list with all phone numbers in the map | G9: List<String> phones = people.values().stream() .flatMap(Collection::stream) .collect(Collectors.toList()); System.out.println(phones);

Sheet Changelog
A1: Date | B1: Version | C1: Implementor | D1: Change
A2: 43126 | B2: 4.11.1 | C2: Mikhail Lavoshnikov | D2: Corrected drop-down list values for "Communication in English" field (Overview!B4)
A3: 43126 | B3: 4.11.1 | C3: Mikhail Lavoshnikov | D3: Corrected maximum score values in hidden column D (Java!D:D)
A4: 43126 | B4: 4.11.1 | C4: Mikhail Lavoshnikov | D4: Added numbering for Java sections
A5: 43170 | B5: 5.1.0 | C5: Oleksii Kvitsynskyi | D5: Testing theory removed
A6: 43170 | B6: 5.1.0 | C6: Oleksii Kvitsynskyi | D6: Added descriptions for grades (junior, regular, etc.)
A7: 43170 | B7: 5.1.0 | C7: Oleksii Kvitsynskyi | D7: Moved changelog to a new tab
A8: 43170 | B8: 5.1.0 | C8: Oleksii Kvitsynskyi | D8: Removed mandatory question for REST
A9: 43170 | B9: 5.1.0 | C9: Oleksii Kvitsynskyi | D9: Removed mandatory mark from all sections not related to core Java (Spring, Hibernate, UNIX, SQL)
A10: 43170 | B10: 5.1.0 | C10: Oleksii Kvitsynskyi | D10: Disclaimer about mandatory sections addede
A11: 43170 | B11: 5.1.0 | C11: Oleksii Kvitsynskyi | D11: Added question about different automated testing types from cross-account, change questions structure based on Michal Kordas proposal
A12: 43170 | B12: 5.1.0 | C12: Oleksii Kvitsynskyi | D12: Added 3 more sections from cross-account
A13: 43213 | B13: 5.1.1 | C13: Roman Torsten | D13: Fixed incorrect link that result in Libre office incompatibility
... A37: 44879 | B37: 8.3.1 | C37: Oleksii Kvitsynskyi | D37: Added Cloud section, separated Spring Boot as a separate section, removed "Typical web applications vulnerabilities and prevention" section

Sheet Technical
A1: Min | B1: Max | C1: Seniority | E1: Expience
A2: 0.01 | B2: 1.33 | C2: insufficient | E2: not assessed
A3: 1.34 | B3: 2 | C3: junior | E3: Yes
A4: 2.01 | B4: 2.33 | C4: junior-regular | E4: No
A5: 2.5 | B5: 3 | C5: regular
A6: 3.01 | B6: 3.5 | C6: regular-senior
A7: 3.51 | B7: 4 | C7: senior
A8: 4.01 | B8: 5 | C8: expert
